{
  "id": "2391770",
  "events": [],
  "reds": {},
  "lineups": null,
  "stats": {
    "donuts": [
      [
        "xG",
        0.25,
        0.57
      ],
      [
        "Držení %",
        44,
        56
      ],
      [
        "Na branku",
        2,
        5
      ],
      [
        "Přesnost %",
        77,
        82
      ],
      [
        "Rohy",
        1,
        3
      ],
      [
        "Fauly",
        9,
        6
      ]
    ],
    "bars": [
      [
        "Střely celkem",
        7,
        12
      ],
      [
        "Střely mimo",
        4,
        4
      ],
      [
        "Zblokované",
        1,
        3
      ],
      [
        "Střely ve vápně",
        3,
        7
      ],
      [
        "Střely zvenku",
        4,
        5
      ],
      [
        "Přihrávky",
        427,
        536
      ],
      [
        "Ofsajdy",
        0,
        0
      ],
      [
        "Přesné přihr.",
        330,
        438
      ],
      [
        "Zákroky brankáře",
        5,
        2
      ],
      [
        "Žluté karty",
        1,
        1
      ],
      [
        "Červené karty",
        0,
        0
      ]
    ]
  },
  "source": "thesportsdb-v2",
  "updatedAt": "2026-06-26T10:10:37.874Z"
}